incognito/__init__.py
incognito/modeling/__init__.py
incognito/modeling/core.py
incognito-0.0.1.dist-info/METADATA
incognito-0.0.1.dist-info/WHEEL
incognito-0.0.1.dist-info/top_level.txt
incognito-0.0.1.dist-info/RECORD
